pvway_sema_abs/__init__.py
pvway_sema_abs/connection_string_provider.py
pvway_sema_abs/semaphore_info.py
pvway_sema_abs/semaphore_service.py
pvway_sema_abs/semaphore_status_enu.py
pvway_sema_abs/sql_role_enu.py
pvway_sema_abs-0.1.3.dist-info/LICENSE
pvway_sema_abs-0.1.3.dist-info/METADATA
pvway_sema_abs-0.1.3.dist-info/WHEEL
pvway_sema_abs-0.1.3.dist-info/RECORD
