Metadata-Version: 2.1
Name: pvway_sema_abs
Version: 0.1.3
Summary: abstraction layer for a semaphore (mutex) service
Author: Pierre Van Wallendael
Author-email: pierrevanwall@gmail.com
Requires-Python: >=3.13,<4.0
Classifier: Programming Language :: Python :: 3
Classifier: Programming Language :: Python :: 3.13
